story_writer/__init__.py
story_writer/_machinery.py
story_writer/_make_pdf.py
story_writer/_streamlit_script.py
story_writer-0.1.1.dist-info/LICENSE
story_writer-0.1.1.dist-info/METADATA
story_writer-0.1.1.dist-info/WHEEL
story_writer-0.1.1.dist-info/entry_points.txt
story_writer-0.1.1.dist-info/top_level.txt
story_writer-0.1.1.dist-info/RECORD
