Metadata-Version: 2.1
Name: story-writer
Version: 0.1.1
Summary: A AI-based story writer Python library which uses OpenAI's chatGPT and Dall-E to generate PDFs with a story and a picture from a prompt and writes them into a PDF.
Home-page: https://github.com/haesleinhuepf/story-writer
Author: Robert Haase
Author-email: robert.haase@tu-dresden.de
License: BSD-3-Clause
Project-URL: Bug Tracker, https://github.com/haesleinhuepf/story-writer/issues
Project-URL: Documentation, https://github.com/haesleinhuepf/story-writer#README.md
Project-URL: Source Code, https://github.com/haesleinhuepf/story-writer
Project-URL: User Support, https://github.com/haesleinhuepf/story-writer/issues
Classifier: Development Status :: 2 - Pre-Alpha
Classifier: Intended Audience :: Developers
Classifier: License :: OSI Approved :: BSD License
Classifier: Operating System :: OS Independent
Classifier: Programming Language :: Python
Classifier: Programming Language :: Python :: 3
Classifier: Programming Language :: Python :: 3 :: Only
Classifier: Programming Language :: Python :: 3.9
Classifier: Programming Language :: Python :: 3.10
Requires-Python: >=3.9
License-File: LICENSE
Requires-Dist: openai >=1.2.0
Requires-Dist: reportlab
Requires-Dist: scikit-image
Requires-Dist: numpy
Provides-Extra: testing
Requires-Dist: tox ; extra == 'testing'
Requires-Dist: pytest ; extra == 'testing'
Requires-Dist: pytest-cov ; extra == 'testing'
